{
    "_id": "67346881f6c94c3b1c0cfb32",
    "Course-ID": "noc24-mg118",
    "Discipline": "Management",
    "Course-name": "Business and Sustainable Development",
    "Course-instructor": "Prof. Trupti Mishra",
    "Institute-name": "IIT Bombay",
    "Duration": "4 Weeks",
    "Start-date": "August 19, 2024",
    "End-date": "September 13, 2024",
    "Course-link": "https://onlinecourses.nptel.ac.in/noc24_mg118/preview",
    "NPTEL-URL": "https://nptel.ac.in/courses/110101153",
    "content": "With the advent of emerging climate economy, it is essential for companies to be aware of not only the threats to business-as-usual from changes in the physical and regulatory environments, but also the unique opportunities to achieve competitive advantage from acting proactively in this area.The underlying rationale for the course is to present a vision of the way in which firms include sustainable development as a key component of the decision-making process. It covers briefings on specific sustainable development topics from a business perspective, strategies, tools to incorporate the principle of sustainability into everyday business activities and business opportunities arising from sustainable development."
}